enclose/__main__.py
enclose/converters/__init__.py
enclose/converters/markdown_converter.py
enclose/converters/pdf_converter.py
enclose/core/__init__.py
enclose/core/document_processor.py
enclose/utils/__init__.py
enclose/utils/file_utils.py
enclose/utils/file_validation.py
enclose/utils/html_utils.py
enclose/utils/metadata_utils.py
enclose/utils/ocr_processor.py
enclose-1.0.9.dist-info/LICENSE
enclose-1.0.9.dist-info/METADATA
enclose-1.0.9.dist-info/WHEEL
enclose-1.0.9.dist-info/entry_points.txt
enclose-1.0.9.dist-info/RECORD
