Metadata-Version: 2.3
Name: enclose
Version: 1.0.9
Summary: A modular document processing pipeline for Markdown to PDF/SVG/PNG conversion with OCR
License: Apache-2.0
Author: Tom
Author-email: info@softreck.dev
Requires-Python: >=3.8.1,<4.0.0
Classifier: License :: OSI Approved :: Apache Software License
Classifier: Programming Language :: Python :: 3
Classifier: Programming Language :: Python :: 3.9
Classifier: Programming Language :: Python :: 3.10
Classifier: Programming Language :: Python :: 3.11
Classifier: Programming Language :: Python :: 3.12
Classifier: Programming Language :: Python :: 3.13
Requires-Dist: Pillow (>=10.0.0,<11.0.0)
Requires-Dist: beautifulsoup4 (>=4.12.2,<5.0.0)
Requires-Dist: cairosvg (>=2.7.1,<3.0.0)
Requires-Dist: filetype (>=1.2.0,<2.0.0)
Requires-Dist: lxml (>=4.9.3,<5.0.0)
Requires-Dist: markdown (>=3.4.4,<4.0.0)
Requires-Dist: pdf2image (>=1.17.0,<2.0.0)
Requires-Dist: pydyf (==0.5.0)
Requires-Dist: pytesseract (>=0.3.10,<0.4.0)
Requires-Dist: python-magic (>=0.4.27,<0.5.0)
Requires-Dist: reportlab (>=4.0.4,<5.0.0)
Requires-Dist: weasyprint (==57.2)
Project-URL: Homepage, https://github.com/veridock/enclose
